fs2es_indexer/Fs2EsIndexer.py
fs2es_indexer/__init__.py
fs2es_indexer/fs2es_indexer.py
fs2es_indexer-0.5.0a3.dist-info/entry_points.txt
fs2es_indexer-0.5.0a3.dist-info/WHEEL
fs2es_indexer-0.5.0a3.dist-info/METADATA
fs2es_indexer-0.5.0a3.dist-info/RECORD
