Metadata-Version: 2.1
Name: fs2es-indexer
Version: 0.5.0a3
Summary: Index files and directories into elastic search
Home-page: https://github.com/Ellerhold/fs2es-indexer
License: Proprietary
Author: Matthias Kühne
Author-email: matthias.kuehne@ellerhold.de
Requires-Python: >=3.9,<4.0
Classifier: License :: Other/Proprietary License
Classifier: Programming Language :: Python :: 3
Classifier: Programming Language :: Python :: 3.10
Classifier: Programming Language :: Python :: 3.9
Requires-Dist: PyYAML (>5.0)
Requires-Dist: elasticsearch (>=8.0,<9.0)
Project-URL: Repository, https://github.com/Ellerhold/fs2es-indexer
